dmbiolib.py
dmbiolib-0.3.10.dist-info/LICENSE
dmbiolib-0.3.10.dist-info/METADATA
dmbiolib-0.3.10.dist-info/WHEEL
dmbiolib-0.3.10.dist-info/top_level.txt
dmbiolib-0.3.10.dist-info/RECORD
