Metadata-Version: 2.1
Name: dmbiolib
Version: 0.3.10
Summary: Library of Python functions used in other projects
Home-page: https://github.com/damienmarsic/dmbiolib
Author: Damien Marsic
Author-email: damien.marsic@aliyun.com
Classifier: Programming Language :: Python :: 3
Classifier: License :: OSI Approved :: GNU General Public License v3 (GPLv3)
Classifier: Operating System :: OS Independent
Classifier: Intended Audience :: Science/Research
Classifier: Topic :: Scientific/Engineering :: Bio-Informatics
Requires-Python: >=3.6
License-File: LICENSE
